scraproxy/__init__.py
scraproxy/main.py
scraproxy-0.0.1.dist-info/LICENSE
scraproxy-0.0.1.dist-info/METADATA
scraproxy-0.0.1.dist-info/WHEEL
scraproxy-0.0.1.dist-info/top_level.txt
scraproxy-0.0.1.dist-info/RECORD
