Metadata-Version: 2.1
Name: scraproxy
Version: 0.0.1
Summary: A simple proxy list fetcher
Home-page: https://github.com/andersonqueiroz/scraproxy
Author: Anderson Queiroz
License: UNKNOWN
Platform: UNKNOWN
Classifier: Programming Language :: Python :: 3
Classifier: License :: OSI Approved :: MIT License
Requires-Python: >=3.6
